Metadata-Version: 2.1
Name: sovietJokes-AuroraZiling
Version: 0.0.1
Summary: A library of Soviet jokes
Home-page: https://github.com/AuroraZiling/Soviet-Jokes-Package
Author: Mccree Lee
Author-email: 2935876049@qq.com
License: UNKNOWN
Platform: UNKNOWN
Classifier: Programming Language :: Python :: 3
Classifier: License :: OSI Approved :: MIT License
Classifier: Operating System :: OS Independent
